{
    "Ongoing":{
        "Team1":{

        "name":"Jetha ke Jabaaz",
        "runs":200,
        "over":5.2,
        "wickets":2
    
        },
        "Team2":{

            "name":"11 COMRADES",
            "runs":100,
            "over":8.2,
            "wickets":10
        
            },
        "Comments":{
            
        }},
    "Previous":{
        "match1":{
            "Team1":{

                "name":"",
                "runs":"",
                "over":"",
                "wickets":""
            
                },
                "Team2":{

                    "name":"",
                    "runs":"",
                    "over":"",
                    "wickets":""
                
                    }
            }
        },
     "Teams":{

            "Jetha Ke Jabaz":{
                "Players":{

                    "P1":{
                        "name":"",
                        "runs":"",
                        "wickets":""
                    },
                    "P2":{
                        "name":"",
                        "runs":"",
                        "wickets":""
                    },
                    "P3":{
                        "name":"",
                        "runs":"",
                        "wickets":""
                    },
                    "P4":{
                        "name":"",
                        "runs":"",
                        "wickets":""
                    },
                    "P5":{
                        "name":"",
                        "runs":"",
                        "wickets":""
                    },
                    "P6":{
                        "name":"",
                        "runs":"",
                        "wickets":""
                    },
                    "P7":{
                        "name":"",
                        "runs":"",
                        "wickets":""
                    },
                    "P8":{
                        "name":"",
                        "runs":"",
                        "wickets":""
                    },
                    "P9":{
                        "name":"",
                        "runs":"",
                        "wickets":""
                    },
                    "P10":{
                        "name":"",
                        "runs":"",
                        "wickets":""
                    },
                    "P11":{
                        "name":"",
                        "runs":"",
                        "wickets":""
                    }
                }
            },
            "11 COMRADES":{"Players":{

                "P1":{
                    "name":"",
                    "runs":"",
                    "wickets":""
                },
                "P2":{
                    "name":"",
                    "runs":"",
                    "wickets":""
                },
                "P3":{
                    "name":"",
                    "runs":"",
                    "wickets":""
                },
                "P4":{
                    "name":"",
                    "runs":"",
                    "wickets":""
                },
                "P5":{
                    "name":"",
                    "runs":"",
                    "wickets":""
                },
                "P6":{
                    "name":"",
                    "runs":"",
                    "wickets":""
                },
                "P7":{
                    "name":"",
                    "runs":"",
                    "wickets":""
                },
                "P8":{
                    "name":"",
                    "runs":"",
                    "wickets":""
                },
                "P9":{
                    "name":"",
                    "runs":"",
                    "wickets":""
                },
                "P10":{
                    "name":"",
                    "runs":"",
                    "wickets":""
                },
                "P11":{
                    "name":"",
                    "runs":"",
                    "wickets":""
                }
                }
            },
            "ECE Rangers":{"Players":{

                "P1":{
                    "name":"",
                    "runs":"",
                    "wickets":""
                },
                "P2":{
                    "name":"",
                    "runs":"",
                    "wickets":""
                },
                "P3":{
                    "name":"",
                    "runs":"",
                    "wickets":""
                },
                "P4":{
                    "name":"",
                    "runs":"",
                    "wickets":""
                },
                "P5":{
                    "name":"",
                    "runs":"",
                    "wickets":""
                },
                "P6":{
                    "name":"",
                    "runs":"",
                    "wickets":""
                },
                "P7":{
                    "name":"",
                    "runs":"",
                    "wickets":""
                },
                "P8":{
                    "name":"",
                    "runs":"",
                    "wickets":""
                },
                "P9":{
                    "name":"",
                    "runs":"",
                    "wickets":""
                },
                "P10":{
                    "name":"",
                    "runs":"",
                    "wickets":""
                },
                "P11":{
                    "name":"",
                    "runs":"",
                    "wickets":""
                }
                }},
            "Jhumri Telaiya Express":{"Players":{

                "P1":{
                    "name":"",
                    "runs":"",
                    "wickets":""
                },
                "P2":{
                    "name":"",
                    "runs":"",
                    "wickets":""
                },
                "P3":{
                    "name":"",
                    "runs":"",
                    "wickets":""
                },
                "P4":{
                    "name":"",
                    "runs":"",
                    "wickets":""
                },
                "P5":{
                    "name":"",
                    "runs":"",
                    "wickets":""
                },
                "P6":{
                    "name":"",
                    "runs":"",
                    "wickets":""
                },
                "P7":{
                    "name":"",
                    "runs":"",
                    "wickets":""
                },
                "P8":{
                    "name":"",
                    "runs":"",
                    "wickets":""
                },
                "P9":{
                    "name":"",
                    "runs":"",
                    "wickets":""
                },
                "P10":{
                    "name":"",
                    "runs":"",
                    "wickets":""
                },
                "P11":{
                    "name":"",
                    "runs":"",
                    "wickets":""
                }
                }},
            "THE BOYZZ":{"Players":{

                "P1":{
                    "name":"",
                    "runs":"",
                    "wickets":""
                },
                "P2":{
                    "name":"",
                    "runs":"",
                    "wickets":""
                },
                "P3":{
                    "name":"",
                    "runs":"",
                    "wickets":""
                },
                "P4":{
                    "name":"",
                    "runs":"",
                    "wickets":""
                },
                "P5":{
                    "name":"",
                    "runs":"",
                    "wickets":""
                },
                "P6":{
                    "name":"",
                    "runs":"",
                    "wickets":""
                },
                "P7":{
                    "name":"",
                    "runs":"",
                    "wickets":""
                },
                "P8":{
                    "name":"",
                    "runs":"",
                    "wickets":""
                },
                "P9":{
                    "name":"",
                    "runs":"",
                    "wickets":""
                },
                "P10":{
                    "name":"",
                    "runs":"",
                    "wickets":""
                },
                "P11":{
                    "name":"",
                    "runs":"",
                    "wickets":""
                }
                }},
            "ECE strikers":{"Players":{

                "P1":{
                    "name":"",
                    "runs":"",
                    "wickets":""
                },
                "P2":{
                    "name":"",
                    "runs":"",
                    "wickets":""
                },
                "P3":{
                    "name":"",
                    "runs":"",
                    "wickets":""
                },
                "P4":{
                    "name":"",
                    "runs":"",
                    "wickets":""
                },
                "P5":{
                    "name":"",
                    "runs":"",
                    "wickets":""
                },
                "P6":{
                    "name":"",
                    "runs":"",
                    "wickets":""
                },
                "P7":{
                    "name":"",
                    "runs":"",
                    "wickets":""
                },
                "P8":{
                    "name":"",
                    "runs":"",
                    "wickets":""
                },
                "P9":{
                    "name":"",
                    "runs":"",
                    "wickets":""
                },
                "P10":{
                    "name":"",
                    "runs":"",
                    "wickets":""
                },
                "P11":{
                    "name":"",
                    "runs":"",
                    "wickets":""
                }
                }}

        }
    }

